CHANGES.rst
CONTRIBUTORS.rst
DEVELOP.rst
LICENSE.rst
MANIFEST.in
README.rst
setup.cfg
setup.py
docs/index.rst
src/readset/__init__.py
src/readset/__init__.pyo
src/readset.i18n.egg-info/PKG-INFO
src/readset.i18n.egg-info/SOURCES.txt
src/readset.i18n.egg-info/dependency_links.txt
src/readset.i18n.egg-info/entry_points.txt
src/readset.i18n.egg-info/namespace_packages.txt
src/readset.i18n.egg-info/not-zip-safe
src/readset.i18n.egg-info/requires.txt
src/readset.i18n.egg-info/top_level.txt
src/readset/i18n/__init__.py
src/readset/i18n/configure.zcml
src/readset/i18n/normalizer/__init__.py
src/readset/i18n/normalizer/configure.zcml
src/readset/i18n/normalizer/zh.py