Metadata-Version: 1.1
Name: readset.i18n
Version: 1.0
Summary: This package provides a Normalizer for Chinese character
Home-page: https://pypi.org/project/readset.i18n
Author: Jian Aijun
Author-email: jianaijun@gmail.com
License: GPL version 2
Keywords: Python Plone i18n i10n normalizer
Platform: UNKNOWN
Classifier: Development Status :: 5 - Production/Stable
Classifier: Environment :: Web Environment
Classifier: Framework :: Plone
Classifier: Framework :: Plone :: 4.3
Classifier: Framework :: Plone :: 5.0
Classifier: Framework :: Plone :: 5.1
Classifier: Programming Language :: Python
Classifier: Programming Language :: Python :: 2.7
Classifier: Programming Language :: Python :: 3
Classifier: Operating System :: OS Independent
Classifier: License :: OSI Approved :: GNU General Public License v2 (GPLv2)
Classifier: Natural Language :: Chinese (Simplified)
Classifier: Natural Language :: Chinese (Traditional)
Classifier: Topic :: Software Development :: Build Tools
